{
  "url": "https://sendaiframework-mtr.undrr.org/",
  "requestedUrl": "https://sendaiframework-mtr.undrr.org/",
  "timestamp": 1758035594780,
  "ranks": {
    "hundos": 5,
    "performance": 4,
    "accessibility": 3,
    "cumulative": 5
  },
  "lighthouse": {
    "version": "12.8.2",
    "performance": 0.76,
    "accessibility": 0.91,
    "bestPractices": 0.61,
    "seo": 0.85,
    "total": 313
  },
  "firstContentfulPaint": 1913.5205,
  "speedIndex": 4617.832360167195,
  "largestContentfulPaint": 5125.3205,
  "totalBlockingTime": 116,
  "cumulativeLayoutShift": 0.00863908086026141,
  "timeToInteractive": 12736.665525,
  "maxPotentialFirstInputDelay": 170,
  "timeToFirstByte": 633.377,
  "weight": {
    "summary": "59 requests • 2.7 MiB",
    "total": 2820219,
    "image": 495188,
    "imageCount": 11,
    "script": 612241,
    "scriptCount": 25,
    "document": 13544,
    "font": 577911,
    "fontCount": 6,
    "stylesheet": 81471,
    "stylesheetCount": 6,
    "thirdParty": 929208,
    "thirdPartyCount": 8
  },
  "run": {
    "number": 1,
    "total": 3
  },
  "sidequests": {
    "-weight.total": 12,
    "+weight.total": 2,
    "-weight.document": 6,
    "+weight.document": 8,
    "-weight.script": 9,
    "+weight.script": 5,
    "-weight.image": 11,
    "+weight.image": 3,
    "-weight.font": 12,
    "+weight.font": 2,
    "+weight.fontCount": 6,
    "-timeToFirstByte": 11,
    "-totalBlockingTime": 1,
    "-largestContentfulPaint": 5
  },
  "axe": {
    "passes": 49,
    "violations": 2
  }
}