{
  "url": "https://globalplatform.undrr.org/",
  "requestedUrl": "https://globalplatform.undrr.org/",
  "timestamp": 1677503418047,
  "ranks": {
    "hundos": 2,
    "performance": 5,
    "accessibility": 1,
    "cumulative": 2
  },
  "lighthouse": {
    "version": "10.0.1",
    "performance": 0.36,
    "accessibility": 0.93,
    "bestPractices": 0.92,
    "seo": 0.85,
    "total": 306
  },
  "firstContentfulPaint": 3838.2860000000005,
  "firstMeaningfulPaint": 3838.2860000000005,
  "speedIndex": 19379.961817529445,
  "largestContentfulPaint": 6831.366500000001,
  "totalBlockingTime": 1180.9999999999982,
  "cumulativeLayoutShift": 0.026715516646647758,
  "timeToInteractive": 19981.695499999998,
  "maxPotentialFirstInputDelay": 648.9999999999982,
  "timeToFirstByte": 6531.229,
  "weight": {
    "summary": "72 requests • 3,414 KiB",
    "total": 3496354,
    "image": 925259,
    "imageCount": 13,
    "script": 2063716,
    "scriptCount": 23,
    "document": 75318,
    "font": 166721,
    "fontCount": 11,
    "stylesheet": 217546,
    "stylesheetCount": 6,
    "thirdParty": 1723260,
    "thirdPartyCount": 54
  },
  "run": {
    "number": 2,
    "total": 2
  },
  "sidequests": {
    "-weight.total": 2,
    "+weight.total": 10,
    "-weight.document": 3,
    "+weight.document": 9,
    "-weight.script": 4,
    "+weight.script": 8,
    "-weight.image": 2,
    "+weight.image": 10,
    "-weight.font": 2,
    "+weight.font": 10,
    "+weight.fontCount": 7,
    "-timeToFirstByte": 10,
    "-totalBlockingTime": 5,
    "-largestContentfulPaint": 3
  },
  "axe": {
    "passes": 801,
    "violations": 31
  }
}